govee_led_wez/__init__.py
govee_led_wez/ble.py
govee_led_wez/color.py
govee_led_wez/govee.py
govee_led_wez/http.py
govee_led_wez/kelvin_rgb.py
govee_led_wez/models.py
govee_led_wez-0.0.14.dist-info/METADATA
govee_led_wez-0.0.14.dist-info/WHEEL
govee_led_wez-0.0.14.dist-info/licenses/LICENSE
govee_led_wez-0.0.14.dist-info/RECORD
