Metadata-Version: 2.1
Name: govee_led_wez
Version: 0.0.14
Summary: Control Govee LED lights
Project-URL: Homepage, https://github.com/wez/govee-py
Project-URL: Bug Tracker, https://github.com/wez/govee-py/issues
Author-email: Wez Furlong <wez@wezfurlong.org>
License-File: LICENSE
Classifier: License :: OSI Approved :: MIT License
Classifier: Operating System :: OS Independent
Classifier: Programming Language :: Python :: 3
Requires-Python: >=3.8
Requires-Dist: aiohttp>=3.7.1
Requires-Dist: bleak-retry-connector>=2.8.5
Requires-Dist: bleak>=0.19.0
Requires-Dist: certifi>=2021.10.8
Provides-Extra: dev
Requires-Dist: mypy; extra == 'dev'
Requires-Dist: pylint; extra == 'dev'
Provides-Extra: test
Requires-Dist: pytest; extra == 'test'
Requires-Dist: pytest-asyncio; extra == 'test'
